noid/__init__.py
noid/pynoid.py
noid_mint-0.0.3.data/scripts/noid
noid_mint-0.0.3.dist-info/METADATA
noid_mint-0.0.3.dist-info/WHEEL
noid_mint-0.0.3.dist-info/top_level.txt
noid_mint-0.0.3.dist-info/RECORD
