Metadata-Version: 2.1
Name: noid-mint
Version: 0.0.3
Summary: Mint NOID
Home-page: https://github.com/vt-digital-libraries-platform/NOID-mint
Author: Yinlin Chen, Tingting Jiang, Lee Hunter, Jim Tuttle
Author-email: ylchen@vt.edu, virjtt03@vt.edu, whunter@vt.edu, jjt@vt.edu
License: MIT
Platform: UNKNOWN
Classifier: Programming Language :: Python :: 3.6
Classifier: License :: OSI Approved :: MIT License
Classifier: Operating System :: OS Independent
Requires-Dist: pyyaml
